biolink_model_pydantic/__init__.py
biolink_model_pydantic/model.py
biolink_model_pydantic-0.1.11.dist-info/WHEEL
biolink_model_pydantic-0.1.11.dist-info/METADATA
biolink_model_pydantic-0.1.11.dist-info/RECORD
