Metadata-Version: 1.1
Name: biolink_model_pydantic
Version: 0.1.11
Summary: Pydantic dataclasses for the Biolink model
Home-page: https://github.com/kshefchek/biolink-model-pydantic
Author: The Monarch Initiative
Author-email: info@monarchinitiative.org
